darfortie/__init__.py
darfortie/darfortie_main.py
darfortie/darfortie_params.py
darfortie/darfortie_previous_file.py
darfortie-1.0.2.dist-info/LICENSE
darfortie-1.0.2.dist-info/METADATA
darfortie-1.0.2.dist-info/WHEEL
darfortie-1.0.2.dist-info/entry_points.txt
darfortie-1.0.2.dist-info/top_level.txt
darfortie-1.0.2.dist-info/RECORD
