Metadata-Version: 2.1
Name: darfortie
Version: 1.0.2
Summary: A utility that extends and simplifies using dar (Disk ARchive) for doing routine incremental backups.
Home-page: https://github.com/kagalle/darfortie
Author: Kenneth Galle
Author-email: ken.galle@rainshowers.org
License: UNKNOWN
Keywords: dar incremental backup
Platform: UNKNOWN
Classifier: Development Status :: 4 - Beta
Classifier: Environment :: Console
Classifier: Intended Audience :: End Users/Desktop
Classifier: Intended Audience :: System Administrators
Classifier: License :: OSI Approved :: GNU General Public License v3 (GPLv3)
Classifier: Natural Language :: English
Classifier: Operating System :: MacOS :: MacOS X
Classifier: Operating System :: Microsoft :: Windows
Classifier: Operating System :: POSIX :: BSD :: FreeBSD
Classifier: Operating System :: POSIX :: Linux
Classifier: Programming Language :: Python
Classifier: Programming Language :: Python :: 2
Classifier: Programming Language :: Python :: 3
Classifier: Topic :: System :: Archiving :: Backup
